[
	{
		"url": "https://hci.social/api/v1/statuses/111491794208793604",
		"data": {
			"id": "111491794208793604",
			"created_at": "2023-11-29T03:49:30.034Z",
			"in_reply_to_id": null,
			"in_reply_to_account_id": null,
			"sensitive": false,
			"spoiler_text": "",
			"visibility": "unlisted",
			"language": "en",
			"uri": "https://hci.social/users/ryanatkn/statuses/111491794208793604",
			"url": "https://hci.social/@ryanatkn/111491794208793604",
			"replies_count": 2,
			"reblogs_count": 0,
			"favourites_count": 0,
			"edited_at": null,
			"favourited": false,
			"reblogged": false,
			"muted": false,
			"bookmarked": false,
			"pinned": false,
			"content": "\u003cp\u003ethis post is embedded on \u003ca href=\"https://mastodon.fuz.dev/\" target=\"_blank\" rel=\"nofollow noopener noreferrer\" translate=\"no\"\u003e\u003cspan class=\"invisible\"\u003ehttps://\u003c/span\u003e\u003cspan class=\"\"\u003emastodon.fuz.dev/\u003c/span\u003e\u003cspan class=\"invisible\"\u003e\u003c/span\u003e\u003c/a\u003e using a Svelte component\u003c/p\u003e\u003cp\u003ethe code is rough and early but works if you\u0026#39;re reading this on mastodon.fuz.dev - \u003ca href=\"https://github.com/fuz-dev/fuz_mastodon\" target=\"_blank\" rel=\"nofollow noopener noreferrer\" translate=\"no\"\u003e\u003cspan class=\"invisible\"\u003ehttps://\u003c/span\u003e\u003cspan class=\"ellipsis\"\u003egithub.com/fuz-dev/fuz_mastodo\u003c/span\u003e\u003cspan class=\"invisible\"\u003en\u003c/span\u003e\u003c/a\u003e\u003c/p\u003e\u003cp\u003ereplies to this post that I favourite will appear on \u003ca href=\"https://mastodon.fuz.dev/\" target=\"_blank\" rel=\"nofollow noopener noreferrer\" translate=\"no\"\u003e\u003cspan class=\"invisible\"\u003ehttps://\u003c/span\u003e\u003cspan class=\"\"\u003emastodon.fuz.dev/\u003c/span\u003e\u003cspan class=\"invisible\"\u003e\u003c/span\u003e\u003c/a\u003e\u003c/p\u003e",
			"filtered": [],
			"reblog": null,
			"application": {"name": "Web", "website": null},
			"account": {
				"id": "109337961591161088",
				"username": "ryanatkn",
				"acct": "ryanatkn",
				"display_name": "Ryan Atkinson",
				"locked": false,
				"bot": false,
				"discoverable": true,
				"group": false,
				"created_at": "2022-11-13T00:00:00.000Z",
				"note": "\u003cp\u003eopen source web dev, working on felt.dev, fuz.dev, grogarden.org, and spiderspace.org, \u003ca href=\"https://hci.social/tags/ActivityStreams\" class=\"mention hashtag\" rel=\"tag\"\u003e#\u003cspan\u003eActivityStreams\u003c/span\u003e\u003c/a\u003e \u003ca href=\"https://hci.social/tags/ActivityPub\" class=\"mention hashtag\" rel=\"tag\"\u003e#\u003cspan\u003eActivityPub\u003c/span\u003e\u003c/a\u003e \u003ca href=\"https://hci.social/tags/JS\" class=\"mention hashtag\" rel=\"tag\"\u003e#\u003cspan\u003eJS\u003c/span\u003e\u003c/a\u003e \u003ca href=\"https://hci.social/tags/CSS\" class=\"mention hashtag\" rel=\"tag\"\u003e#\u003cspan\u003eCSS\u003c/span\u003e\u003c/a\u003e \u003ca href=\"https://hci.social/tags/HTML\" class=\"mention hashtag\" rel=\"tag\"\u003e#\u003cspan\u003eHTML\u003c/span\u003e\u003c/a\u003e \u003ca href=\"https://hci.social/tags/svelte\" class=\"mention hashtag\" rel=\"tag\"\u003e#\u003cspan\u003esvelte\u003c/span\u003e\u003c/a\u003e \u003ca href=\"https://hci.social/tags/SvelteKit\" class=\"mention hashtag\" rel=\"tag\"\u003e#\u003cspan\u003eSvelteKit\u003c/span\u003e\u003c/a\u003e\u003c/p\u003e",
				"url": "https://hci.social/@ryanatkn",
				"uri": "https://hci.social/users/ryanatkn",
				"avatar": "https://storage.googleapis.com/hci-social-storage/accounts/avatars/109/337/961/591/161/088/original/c3fe65d180008d03.png",
				"avatar_static": "https://storage.googleapis.com/hci-social-storage/accounts/avatars/109/337/961/591/161/088/original/c3fe65d180008d03.png",
				"header": "https://storage.googleapis.com/hci-social-storage/accounts/headers/109/337/961/591/161/088/original/e002ff8d78a865ce.jpg",
				"header_static": "https://storage.googleapis.com/hci-social-storage/accounts/headers/109/337/961/591/161/088/original/e002ff8d78a865ce.jpg",
				"followers_count": 37,
				"following_count": 96,
				"statuses_count": 13,
				"last_status_at": "2023-11-29",
				"noindex": false,
				"emojis": [],
				"roles": [],
				"fields": [
					{
						"name": "home",
						"value": "\u003ca href=\"https://www.ryanatkn.com\" target=\"_blank\" rel=\"nofollow noopener noreferrer me\" translate=\"no\"\u003e\u003cspan class=\"invisible\"\u003ehttps://www.\u003c/span\u003e\u003cspan class=\"\"\u003eryanatkn.com\u003c/span\u003e\u003cspan class=\"invisible\"\u003e\u003c/span\u003e\u003c/a\u003e",
						"verified_at": "2022-11-13T18:48:11.596+00:00"
					},
					{
						"name": "code",
						"value": "\u003ca href=\"https://github.com/ryanatkn\" target=\"_blank\" rel=\"nofollow noopener noreferrer me\" translate=\"no\"\u003e\u003cspan class=\"invisible\"\u003ehttps://\u003c/span\u003e\u003cspan class=\"\"\u003egithub.com/ryanatkn\u003c/span\u003e\u003cspan class=\"invisible\"\u003e\u003c/span\u003e\u003c/a\u003e",
						"verified_at": "2022-11-13T19:12:25.810+00:00"
					},
					{
						"name": "feltjs",
						"value": "\u003ca href=\"https://www.felt.dev\" target=\"_blank\" rel=\"nofollow noopener noreferrer me\" translate=\"no\"\u003e\u003cspan class=\"invisible\"\u003ehttps://www.\u003c/span\u003e\u003cspan class=\"\"\u003efelt.dev\u003c/span\u003e\u003cspan class=\"invisible\"\u003e\u003c/span\u003e\u003c/a\u003e",
						"verified_at": "2023-09-20T03:27:04.768+00:00"
					},
					{
						"name": "youtube",
						"value": "\u003ca href=\"https://youtube.com/@ryanatkn\" target=\"_blank\" rel=\"nofollow noopener noreferrer me\" translate=\"no\"\u003e\u003cspan class=\"invisible\"\u003ehttps://\u003c/span\u003e\u003cspan class=\"\"\u003eyoutube.com/@ryanatkn\u003c/span\u003e\u003cspan class=\"invisible\"\u003e\u003c/span\u003e\u003c/a\u003e",
						"verified_at": null
					}
				]
			},
			"media_attachments": [],
			"mentions": [],
			"tags": [],
			"emojis": [],
			"card": {
				"url": "https://mastodon.fuz.dev/",
				"title": "@fuz.dev/fuz_mastodon",
				"description": "",
				"language": "en",
				"type": "link",
				"author_name": "",
				"author_url": "",
				"provider_name": "",
				"provider_url": "",
				"html": "",
				"width": 0,
				"height": 0,
				"image": null,
				"image_description": "",
				"embed_url": "",
				"blurhash": null,
				"published_at": null
			},
			"poll": null
		}
	},
	{
		"url": "https://hci.social/api/v1/statuses/111491794208793604/context",
		"data": {
			"ancestors": [],
			"descendants": [
				{
					"id": "111491816409848117",
					"created_at": "2023-11-29T03:55:08.790Z",
					"in_reply_to_id": "111491794208793604",
					"in_reply_to_account_id": "109337961591161088",
					"sensitive": false,
					"spoiler_text": "",
					"visibility": "unlisted",
					"language": "en",
					"uri": "https://hci.social/users/ryanatkn/statuses/111491816409848117",
					"url": "https://hci.social/@ryanatkn/111491816409848117",
					"replies_count": 1,
					"reblogs_count": 0,
					"favourites_count": 1,
					"edited_at": null,
					"favourited": true,
					"reblogged": false,
					"muted": false,
					"bookmarked": false,
					"pinned": false,
					"content": "\u003cp\u003e(unlisted reply for demo purposes, please ignore)\u003c/p\u003e",
					"filtered": [],
					"reblog": null,
					"application": {"name": "Web", "website": null},
					"account": {
						"id": "109337961591161088",
						"username": "ryanatkn",
						"acct": "ryanatkn",
						"display_name": "Ryan Atkinson",
						"locked": false,
						"bot": false,
						"discoverable": true,
						"group": false,
						"created_at": "2022-11-13T00:00:00.000Z",
						"note": "\u003cp\u003eopen source web dev, working on felt.dev, fuz.dev, grogarden.org, and spiderspace.org, \u003ca href=\"https://hci.social/tags/ActivityStreams\" class=\"mention hashtag\" rel=\"tag\"\u003e#\u003cspan\u003eActivityStreams\u003c/span\u003e\u003c/a\u003e \u003ca href=\"https://hci.social/tags/ActivityPub\" class=\"mention hashtag\" rel=\"tag\"\u003e#\u003cspan\u003eActivityPub\u003c/span\u003e\u003c/a\u003e \u003ca href=\"https://hci.social/tags/JS\" class=\"mention hashtag\" rel=\"tag\"\u003e#\u003cspan\u003eJS\u003c/span\u003e\u003c/a\u003e \u003ca href=\"https://hci.social/tags/CSS\" class=\"mention hashtag\" rel=\"tag\"\u003e#\u003cspan\u003eCSS\u003c/span\u003e\u003c/a\u003e \u003ca href=\"https://hci.social/tags/HTML\" class=\"mention hashtag\" rel=\"tag\"\u003e#\u003cspan\u003eHTML\u003c/span\u003e\u003c/a\u003e \u003ca href=\"https://hci.social/tags/svelte\" class=\"mention hashtag\" rel=\"tag\"\u003e#\u003cspan\u003esvelte\u003c/span\u003e\u003c/a\u003e \u003ca href=\"https://hci.social/tags/SvelteKit\" class=\"mention hashtag\" rel=\"tag\"\u003e#\u003cspan\u003eSvelteKit\u003c/span\u003e\u003c/a\u003e\u003c/p\u003e",
						"url": "https://hci.social/@ryanatkn",
						"uri": "https://hci.social/users/ryanatkn",
						"avatar": "https://storage.googleapis.com/hci-social-storage/accounts/avatars/109/337/961/591/161/088/original/c3fe65d180008d03.png",
						"avatar_static": "https://storage.googleapis.com/hci-social-storage/accounts/avatars/109/337/961/591/161/088/original/c3fe65d180008d03.png",
						"header": "https://storage.googleapis.com/hci-social-storage/accounts/headers/109/337/961/591/161/088/original/e002ff8d78a865ce.jpg",
						"header_static": "https://storage.googleapis.com/hci-social-storage/accounts/headers/109/337/961/591/161/088/original/e002ff8d78a865ce.jpg",
						"followers_count": 37,
						"following_count": 96,
						"statuses_count": 13,
						"last_status_at": "2023-11-29",
						"noindex": false,
						"emojis": [],
						"roles": [],
						"fields": [
							{
								"name": "home",
								"value": "\u003ca href=\"https://www.ryanatkn.com\" target=\"_blank\" rel=\"nofollow noopener noreferrer me\" translate=\"no\"\u003e\u003cspan class=\"invisible\"\u003ehttps://www.\u003c/span\u003e\u003cspan class=\"\"\u003eryanatkn.com\u003c/span\u003e\u003cspan class=\"invisible\"\u003e\u003c/span\u003e\u003c/a\u003e",
								"verified_at": "2022-11-13T18:48:11.596+00:00"
							},
							{
								"name": "code",
								"value": "\u003ca href=\"https://github.com/ryanatkn\" target=\"_blank\" rel=\"nofollow noopener noreferrer me\" translate=\"no\"\u003e\u003cspan class=\"invisible\"\u003ehttps://\u003c/span\u003e\u003cspan class=\"\"\u003egithub.com/ryanatkn\u003c/span\u003e\u003cspan class=\"invisible\"\u003e\u003c/span\u003e\u003c/a\u003e",
								"verified_at": "2022-11-13T19:12:25.810+00:00"
							},
							{
								"name": "feltjs",
								"value": "\u003ca href=\"https://www.felt.dev\" target=\"_blank\" rel=\"nofollow noopener noreferrer me\" translate=\"no\"\u003e\u003cspan class=\"invisible\"\u003ehttps://www.\u003c/span\u003e\u003cspan class=\"\"\u003efelt.dev\u003c/span\u003e\u003cspan class=\"invisible\"\u003e\u003c/span\u003e\u003c/a\u003e",
								"verified_at": "2023-09-20T03:27:04.768+00:00"
							},
							{
								"name": "youtube",
								"value": "\u003ca href=\"https://youtube.com/@ryanatkn\" target=\"_blank\" rel=\"nofollow noopener noreferrer me\" translate=\"no\"\u003e\u003cspan class=\"invisible\"\u003ehttps://\u003c/span\u003e\u003cspan class=\"\"\u003eyoutube.com/@ryanatkn\u003c/span\u003e\u003cspan class=\"invisible\"\u003e\u003c/span\u003e\u003c/a\u003e",
								"verified_at": null
							}
						]
					},
					"media_attachments": [],
					"mentions": [],
					"tags": [],
					"emojis": [],
					"card": null,
					"poll": null
				},
				{
					"id": "111491828406951988",
					"created_at": "2023-11-29T03:58:11.852Z",
					"in_reply_to_id": "111491816409848117",
					"in_reply_to_account_id": "109337961591161088",
					"sensitive": false,
					"spoiler_text": "",
					"visibility": "unlisted",
					"language": "en",
					"uri": "https://hci.social/users/ryanatkn/statuses/111491828406951988",
					"url": "https://hci.social/@ryanatkn/111491828406951988",
					"replies_count": 0,
					"reblogs_count": 0,
					"favourites_count": 1,
					"edited_at": null,
					"favourited": true,
					"reblogged": false,
					"muted": false,
					"bookmarked": false,
					"pinned": false,
					"content": "\u003cp\u003e(unlisted reply to a reply for demo purposes, please ignore)\u003c/p\u003e",
					"filtered": [],
					"reblog": null,
					"application": {"name": "Web", "website": null},
					"account": {
						"id": "109337961591161088",
						"username": "ryanatkn",
						"acct": "ryanatkn",
						"display_name": "Ryan Atkinson",
						"locked": false,
						"bot": false,
						"discoverable": true,
						"group": false,
						"created_at": "2022-11-13T00:00:00.000Z",
						"note": "\u003cp\u003eopen source web dev, working on felt.dev, fuz.dev, grogarden.org, and spiderspace.org, \u003ca href=\"https://hci.social/tags/ActivityStreams\" class=\"mention hashtag\" rel=\"tag\"\u003e#\u003cspan\u003eActivityStreams\u003c/span\u003e\u003c/a\u003e \u003ca href=\"https://hci.social/tags/ActivityPub\" class=\"mention hashtag\" rel=\"tag\"\u003e#\u003cspan\u003eActivityPub\u003c/span\u003e\u003c/a\u003e \u003ca href=\"https://hci.social/tags/JS\" class=\"mention hashtag\" rel=\"tag\"\u003e#\u003cspan\u003eJS\u003c/span\u003e\u003c/a\u003e \u003ca href=\"https://hci.social/tags/CSS\" class=\"mention hashtag\" rel=\"tag\"\u003e#\u003cspan\u003eCSS\u003c/span\u003e\u003c/a\u003e \u003ca href=\"https://hci.social/tags/HTML\" class=\"mention hashtag\" rel=\"tag\"\u003e#\u003cspan\u003eHTML\u003c/span\u003e\u003c/a\u003e \u003ca href=\"https://hci.social/tags/svelte\" class=\"mention hashtag\" rel=\"tag\"\u003e#\u003cspan\u003esvelte\u003c/span\u003e\u003c/a\u003e \u003ca href=\"https://hci.social/tags/SvelteKit\" class=\"mention hashtag\" rel=\"tag\"\u003e#\u003cspan\u003eSvelteKit\u003c/span\u003e\u003c/a\u003e\u003c/p\u003e",
						"url": "https://hci.social/@ryanatkn",
						"uri": "https://hci.social/users/ryanatkn",
						"avatar": "https://storage.googleapis.com/hci-social-storage/accounts/avatars/109/337/961/591/161/088/original/c3fe65d180008d03.png",
						"avatar_static": "https://storage.googleapis.com/hci-social-storage/accounts/avatars/109/337/961/591/161/088/original/c3fe65d180008d03.png",
						"header": "https://storage.googleapis.com/hci-social-storage/accounts/headers/109/337/961/591/161/088/original/e002ff8d78a865ce.jpg",
						"header_static": "https://storage.googleapis.com/hci-social-storage/accounts/headers/109/337/961/591/161/088/original/e002ff8d78a865ce.jpg",
						"followers_count": 37,
						"following_count": 96,
						"statuses_count": 13,
						"last_status_at": "2023-11-29",
						"noindex": false,
						"emojis": [],
						"roles": [],
						"fields": [
							{
								"name": "home",
								"value": "\u003ca href=\"https://www.ryanatkn.com\" target=\"_blank\" rel=\"nofollow noopener noreferrer me\" translate=\"no\"\u003e\u003cspan class=\"invisible\"\u003ehttps://www.\u003c/span\u003e\u003cspan class=\"\"\u003eryanatkn.com\u003c/span\u003e\u003cspan class=\"invisible\"\u003e\u003c/span\u003e\u003c/a\u003e",
								"verified_at": "2022-11-13T18:48:11.596+00:00"
							},
							{
								"name": "code",
								"value": "\u003ca href=\"https://github.com/ryanatkn\" target=\"_blank\" rel=\"nofollow noopener noreferrer me\" translate=\"no\"\u003e\u003cspan class=\"invisible\"\u003ehttps://\u003c/span\u003e\u003cspan class=\"\"\u003egithub.com/ryanatkn\u003c/span\u003e\u003cspan class=\"invisible\"\u003e\u003c/span\u003e\u003c/a\u003e",
								"verified_at": "2022-11-13T19:12:25.810+00:00"
							},
							{
								"name": "feltjs",
								"value": "\u003ca href=\"https://www.felt.dev\" target=\"_blank\" rel=\"nofollow noopener noreferrer me\" translate=\"no\"\u003e\u003cspan class=\"invisible\"\u003ehttps://www.\u003c/span\u003e\u003cspan class=\"\"\u003efelt.dev\u003c/span\u003e\u003cspan class=\"invisible\"\u003e\u003c/span\u003e\u003c/a\u003e",
								"verified_at": "2023-09-20T03:27:04.768+00:00"
							},
							{
								"name": "youtube",
								"value": "\u003ca href=\"https://youtube.com/@ryanatkn\" target=\"_blank\" rel=\"nofollow noopener noreferrer me\" translate=\"no\"\u003e\u003cspan class=\"invisible\"\u003ehttps://\u003c/span\u003e\u003cspan class=\"\"\u003eyoutube.com/@ryanatkn\u003c/span\u003e\u003cspan class=\"invisible\"\u003e\u003c/span\u003e\u003c/a\u003e",
								"verified_at": null
							}
						]
					},
					"media_attachments": [],
					"mentions": [],
					"tags": [],
					"emojis": [],
					"card": null,
					"poll": null
				},
				{
					"id": "111491829510427790",
					"created_at": "2023-11-29T03:58:28.689Z",
					"in_reply_to_id": "111491794208793604",
					"in_reply_to_account_id": "109337961591161088",
					"sensitive": false,
					"spoiler_text": "",
					"visibility": "unlisted",
					"language": "en",
					"uri": "https://hci.social/users/ryanatkn/statuses/111491829510427790",
					"url": "https://hci.social/@ryanatkn/111491829510427790",
					"replies_count": 0,
					"reblogs_count": 0,
					"favourites_count": 1,
					"edited_at": null,
					"favourited": true,
					"reblogged": false,
					"muted": false,
					"bookmarked": false,
					"pinned": false,
					"content": "\u003cp\u003e(unlisted second reply for demo purposes, please ignore)\u003c/p\u003e",
					"filtered": [],
					"reblog": null,
					"application": {"name": "Web", "website": null},
					"account": {
						"id": "109337961591161088",
						"username": "ryanatkn",
						"acct": "ryanatkn",
						"display_name": "Ryan Atkinson",
						"locked": false,
						"bot": false,
						"discoverable": true,
						"group": false,
						"created_at": "2022-11-13T00:00:00.000Z",
						"note": "\u003cp\u003eopen source web dev, working on felt.dev, fuz.dev, grogarden.org, and spiderspace.org, \u003ca href=\"https://hci.social/tags/ActivityStreams\" class=\"mention hashtag\" rel=\"tag\"\u003e#\u003cspan\u003eActivityStreams\u003c/span\u003e\u003c/a\u003e \u003ca href=\"https://hci.social/tags/ActivityPub\" class=\"mention hashtag\" rel=\"tag\"\u003e#\u003cspan\u003eActivityPub\u003c/span\u003e\u003c/a\u003e \u003ca href=\"https://hci.social/tags/JS\" class=\"mention hashtag\" rel=\"tag\"\u003e#\u003cspan\u003eJS\u003c/span\u003e\u003c/a\u003e \u003ca href=\"https://hci.social/tags/CSS\" class=\"mention hashtag\" rel=\"tag\"\u003e#\u003cspan\u003eCSS\u003c/span\u003e\u003c/a\u003e \u003ca href=\"https://hci.social/tags/HTML\" class=\"mention hashtag\" rel=\"tag\"\u003e#\u003cspan\u003eHTML\u003c/span\u003e\u003c/a\u003e \u003ca href=\"https://hci.social/tags/svelte\" class=\"mention hashtag\" rel=\"tag\"\u003e#\u003cspan\u003esvelte\u003c/span\u003e\u003c/a\u003e \u003ca href=\"https://hci.social/tags/SvelteKit\" class=\"mention hashtag\" rel=\"tag\"\u003e#\u003cspan\u003eSvelteKit\u003c/span\u003e\u003c/a\u003e\u003c/p\u003e",
						"url": "https://hci.social/@ryanatkn",
						"uri": "https://hci.social/users/ryanatkn",
						"avatar": "https://storage.googleapis.com/hci-social-storage/accounts/avatars/109/337/961/591/161/088/original/c3fe65d180008d03.png",
						"avatar_static": "https://storage.googleapis.com/hci-social-storage/accounts/avatars/109/337/961/591/161/088/original/c3fe65d180008d03.png",
						"header": "https://storage.googleapis.com/hci-social-storage/accounts/headers/109/337/961/591/161/088/original/e002ff8d78a865ce.jpg",
						"header_static": "https://storage.googleapis.com/hci-social-storage/accounts/headers/109/337/961/591/161/088/original/e002ff8d78a865ce.jpg",
						"followers_count": 37,
						"following_count": 96,
						"statuses_count": 13,
						"last_status_at": "2023-11-29",
						"noindex": false,
						"emojis": [],
						"roles": [],
						"fields": [
							{
								"name": "home",
								"value": "\u003ca href=\"https://www.ryanatkn.com\" target=\"_blank\" rel=\"nofollow noopener noreferrer me\" translate=\"no\"\u003e\u003cspan class=\"invisible\"\u003ehttps://www.\u003c/span\u003e\u003cspan class=\"\"\u003eryanatkn.com\u003c/span\u003e\u003cspan class=\"invisible\"\u003e\u003c/span\u003e\u003c/a\u003e",
								"verified_at": "2022-11-13T18:48:11.596+00:00"
							},
							{
								"name": "code",
								"value": "\u003ca href=\"https://github.com/ryanatkn\" target=\"_blank\" rel=\"nofollow noopener noreferrer me\" translate=\"no\"\u003e\u003cspan class=\"invisible\"\u003ehttps://\u003c/span\u003e\u003cspan class=\"\"\u003egithub.com/ryanatkn\u003c/span\u003e\u003cspan class=\"invisible\"\u003e\u003c/span\u003e\u003c/a\u003e",
								"verified_at": "2022-11-13T19:12:25.810+00:00"
							},
							{
								"name": "feltjs",
								"value": "\u003ca href=\"https://www.felt.dev\" target=\"_blank\" rel=\"nofollow noopener noreferrer me\" translate=\"no\"\u003e\u003cspan class=\"invisible\"\u003ehttps://www.\u003c/span\u003e\u003cspan class=\"\"\u003efelt.dev\u003c/span\u003e\u003cspan class=\"invisible\"\u003e\u003c/span\u003e\u003c/a\u003e",
								"verified_at": "2023-09-20T03:27:04.768+00:00"
							},
							{
								"name": "youtube",
								"value": "\u003ca href=\"https://youtube.com/@ryanatkn\" target=\"_blank\" rel=\"nofollow noopener noreferrer me\" translate=\"no\"\u003e\u003cspan class=\"invisible\"\u003ehttps://\u003c/span\u003e\u003cspan class=\"\"\u003eyoutube.com/@ryanatkn\u003c/span\u003e\u003cspan class=\"invisible\"\u003e\u003c/span\u003e\u003c/a\u003e",
								"verified_at": null
							}
						]
					},
					"media_attachments": [],
					"mentions": [],
					"tags": [],
					"emojis": [],
					"card": null,
					"poll": null
				}
			]
		}
	}
]
